shPassGenerator/__init__.py
shPassGenerator/utils.py
shPassGenerator-1.0.6.dist-info/LICENSE
shPassGenerator-1.0.6.dist-info/METADATA
shPassGenerator-1.0.6.dist-info/WHEEL
shPassGenerator-1.0.6.dist-info/top_level.txt
shPassGenerator-1.0.6.dist-info/RECORD
