Metadata-Version: 2.1
Name: shPassGenerator
Version: 1.0.6
Summary: UNKNOWN
Author: Shervin Badanara (shervinbdndev)
Author-email: shervin2234@gmail.com
License: UNKNOWN
Keywords: python,password,password generator,strong password
Platform: UNKNOWN
Classifier: Development Status :: 1 - Planning
Classifier: Intended Audience :: Developers
Classifier: Programming Language :: Python :: 3
Classifier: Operating System :: Unix
Classifier: Operating System :: MacOS :: MacOS X
Classifier: Operating System :: Microsoft :: Windows
License-File: LICENSE
